prospect/__init__.py
prospect/area.py
prospect/assemblage.py
prospect/coverage.py
prospect/feature.py
prospect/layer.py
prospect/plotting.py
prospect/survey.py
prospect/surveyor.py
prospect/surveyunit.py
prospect/team.py
prospect/utils.py
prospect-0.1.0.dist-info/LICENSE
prospect-0.1.0.dist-info/METADATA
prospect-0.1.0.dist-info/WHEEL
prospect-0.1.0.dist-info/top_level.txt
prospect-0.1.0.dist-info/RECORD
