Metadata-Version: 2.1
Name: prospect
Version: 0.1.0
Summary: Archaeological survey simulation
Home-page: UNKNOWN
Author: Jacob Deppen
Author-email: prospect.python@gmail.com
License: UNKNOWN
Project-URL: Bug Reports, https://github.com/deppen8/prospect
Project-URL: Documentation, https://deppen8.github.io/prospect
Keywords: archaeology survey simulation gis fieldwork
Platform: UNKNOWN
Classifier: Development Status :: 4 - Beta
Classifier: Intended Audience :: Science/Research
Classifier: Topic :: Scientific/Engineering
Classifier: Topic :: Scientific/Engineering :: GIS
Classifier: Topic :: Other/Nonlisted Topic
Classifier: License :: OSI Approved :: MIT License
Classifier: Programming Language :: Python :: 3
Requires-Dist: pandas
Requires-Dist: numpy
Requires-Dist: geopandas
Requires-Dist: scipy
Requires-Dist: matplotlib
